{
  "Atrani.ru": {
    "name": "Atrani.ru",
    "propertyId": "properties/353046676",
    "updatedAt": "2026-05-26T08:35:40.975Z",
    "summary7d": {
      "sessions": 319,
      "users": 316,
      "pageViews": 320,
      "avgSessionDuration": 10,
      "bounceRate": 0.8
    },
    "summary30d": {
      "sessions": 1013,
      "users": 958,
      "pageViews": 1092,
      "avgSessionDuration": 20,
      "bounceRate": 0.8
    }
  },
  "Cinereo.it": {
    "name": "Cinereo.it",
    "propertyId": "properties/362803366",
    "updatedAt": "2026-05-26T08:35:41.093Z",
    "summary7d": {
      "sessions": 0,
      "users": 0,
      "pageViews": 0,
      "avgSessionDuration": 0,
      "bounceRate": 0
    },
    "summary30d": {
      "sessions": 15,
      "users": 1,
      "pageViews": 24,
      "avgSessionDuration": 540,
      "bounceRate": 0.4
    }
  },
  "amalfi.day": {
    "name": "amalfi.day",
    "propertyId": "properties/306713351",
    "updatedAt": "2026-05-26T08:35:41.215Z",
    "summary7d": {
      "sessions": 152,
      "users": 95,
      "pageViews": 193,
      "avgSessionDuration": 133,
      "bounceRate": 0.6
    },
    "summary30d": {
      "sessions": 607,
      "users": 314,
      "pageViews": 1044,
      "avgSessionDuration": 234,
      "bounceRate": 0.5
    }
  },
  "guide.amalfi.day": {
    "name": "guide.amalfi.day",
    "propertyId": "properties/533587112",
    "updatedAt": "2026-05-26T08:35:41.291Z",
    "summary7d": {
      "sessions": 66,
      "users": 18,
      "pageViews": 309,
      "avgSessionDuration": 571,
      "bounceRate": 0.3
    },
    "summary30d": {
      "sessions": 190,
      "users": 42,
      "pageViews": 935,
      "avgSessionDuration": 387,
      "bounceRate": 0.3
    }
  },
  "find.amalfi.day": {
    "name": "find.amalfi.day",
    "propertyId": "properties/531159837",
    "updatedAt": "2026-05-26T08:35:41.408Z",
    "summary7d": {
      "sessions": 49,
      "users": 24,
      "pageViews": 108,
      "avgSessionDuration": 303,
      "bounceRate": 0.4
    },
    "summary30d": {
      "sessions": 170,
      "users": 66,
      "pageViews": 366,
      "avgSessionDuration": 280,
      "bounceRate": 0.4
    }
  },
  "Ceramiche Da Mario": {
    "name": "Ceramiche Da Mario",
    "propertyId": "properties/529437415",
    "updatedAt": "2026-05-26T08:35:42.124Z",
    "summary7d": {
      "sessions": 41,
      "users": 36,
      "pageViews": 117,
      "avgSessionDuration": 106,
      "bounceRate": 0.5
    },
    "summary30d": {
      "sessions": 113,
      "users": 97,
      "pageViews": 332,
      "avgSessionDuration": 124,
      "bounceRate": 0.5
    }
  },
  "Moto Excursions": {
    "name": "Moto Excursions",
    "propertyId": "properties/533663747",
    "updatedAt": "2026-05-26T08:35:42.777Z",
    "summary7d": {
      "sessions": 16,
      "users": 8,
      "pageViews": 46,
      "avgSessionDuration": 337,
      "bounceRate": 0.4
    },
    "summary30d": {
      "sessions": 64,
      "users": 43,
      "pageViews": 127,
      "avgSessionDuration": 288,
      "bounceRate": 0.6
    }
  },
  "Katerina": {
    "name": "Katerina",
    "propertyId": "properties/532751253",
    "updatedAt": "2026-05-26T08:35:43.332Z",
    "summary7d": {
      "sessions": 6,
      "users": 5,
      "pageViews": 9,
      "avgSessionDuration": 60,
      "bounceRate": 0.7
    },
    "summary30d": {
      "sessions": 19,
      "users": 10,
      "pageViews": 36,
      "avgSessionDuration": 277,
      "bounceRate": 0.4
    }
  },
  "Masha": {
    "name": "Masha",
    "propertyId": "properties/533601370",
    "updatedAt": "2026-05-26T08:35:44.019Z",
    "summary7d": {
      "sessions": 13,
      "users": 10,
      "pageViews": 16,
      "avgSessionDuration": 171,
      "bounceRate": 0.8
    },
    "summary30d": {
      "sessions": 94,
      "users": 53,
      "pageViews": 134,
      "avgSessionDuration": 127,
      "bounceRate": 0.7
    }
  },
  "Landing (menu.band)": {
    "name": "Landing (menu.band)",
    "propertyId": "properties/529373394",
    "updatedAt": "2026-05-26T08:35:44.332Z",
    "summary7d": {
      "sessions": 0,
      "users": 0,
      "pageViews": 0,
      "avgSessionDuration": 0,
      "bounceRate": 0
    },
    "summary30d": {
      "sessions": 0,
      "users": 0,
      "pageViews": 0,
      "avgSessionDuration": 0,
      "bounceRate": 0
    }
  },
  "Le Palme": {
    "name": "Le Palme",
    "propertyId": "properties/529531573",
    "updatedAt": "2026-05-26T08:35:44.921Z",
    "summary7d": {
      "sessions": 41,
      "users": 25,
      "pageViews": 54,
      "avgSessionDuration": 185,
      "bounceRate": 0.6
    },
    "summary30d": {
      "sessions": 126,
      "users": 68,
      "pageViews": 175,
      "avgSessionDuration": 180,
      "bounceRate": 0.6
    }
  },
  "Birecto": {
    "name": "Birecto",
    "propertyId": "properties/532901805",
    "updatedAt": "2026-05-26T08:35:45.498Z",
    "summary7d": {
      "sessions": 30,
      "users": 18,
      "pageViews": 41,
      "avgSessionDuration": 96,
      "bounceRate": 0.7
    },
    "summary30d": {
      "sessions": 80,
      "users": 55,
      "pageViews": 127,
      "avgSessionDuration": 70,
      "bounceRate": 0.5
    }
  },
  "Vittoria": {
    "name": "Vittoria",
    "propertyId": "properties/533254667",
    "updatedAt": "2026-05-26T08:35:46.155Z",
    "summary7d": {
      "sessions": 124,
      "users": 84,
      "pageViews": 167,
      "avgSessionDuration": 102,
      "bounceRate": 0.7
    },
    "summary30d": {
      "sessions": 439,
      "users": 295,
      "pageViews": 570,
      "avgSessionDuration": 131,
      "bounceRate": 0.6
    }
  }
}